ldap3_directories/__init__.py
ldap3_directories/freeipa.py
ldap3_directories/ldap3_.py
ldap3_directories-0.2.8.dist-info/LICENSE
ldap3_directories-0.2.8.dist-info/METADATA
ldap3_directories-0.2.8.dist-info/WHEEL
ldap3_directories-0.2.8.dist-info/top_level.txt
ldap3_directories-0.2.8.dist-info/RECORD
